MANIFEST.in
README.rst
requirements.txt
setup.cfg
setup.py
djmicrosip_polizas/__init__.py
djmicrosip_polizas/__init__.pyc
djmicrosip_polizas/autocomplete_light_registry.pyc
djmicrosip_polizas/config.pyc
djmicrosip_polizas/models.pyc
djmicrosip_polizas/urls.pyc
djmicrosip_polizas/views.pyc
djmicrosip_polizas.egg-info/PKG-INFO
djmicrosip_polizas.egg-info/SOURCES.txt
djmicrosip_polizas.egg-info/dependency_links.txt
djmicrosip_polizas.egg-info/requires.txt
djmicrosip_polizas.egg-info/top_level.txt
djmicrosip_polizas/modulos/__init__.py
djmicrosip_polizas/modulos/__init__.pyc
djmicrosip_polizas/modulos/polizas/__init__.py
djmicrosip_polizas/modulos/polizas/__init__.pyc
djmicrosip_polizas/modulos/polizas/models.pyc
djmicrosip_polizas/modulos/polizas/urls.pyc
djmicrosip_polizas/modulos/polizas/views.pyc
djmicrosip_polizas/modulos/preferencias/__init__.py
djmicrosip_polizas/modulos/preferencias/__init__.pyc
djmicrosip_polizas/modulos/preferencias/forms.pyc
djmicrosip_polizas/modulos/preferencias/models.pyc
djmicrosip_polizas/modulos/preferencias/urls.pyc
djmicrosip_polizas/modulos/preferencias/views.pyc
djmicrosip_polizas/static/djmicrosip_polizas/js/agrupar_polizas.js
djmicrosip_polizas/static/djmicrosip_polizas/js/polizas.js
djmicrosip_polizas/templates/djmicrosip_polizas/base.html
djmicrosip_polizas/templates/djmicrosip_polizas/index.html
djmicrosip_polizas/templates/djmicrosip_polizas/polizas/poliza_list.html
djmicrosip_polizas/templates/djmicrosip_polizas/polizas/poliza_list_agrupar.html
djmicrosip_polizas/templates/djmicrosip_polizas/preferencias/preferencias.html