Metadata-Version: 1.1
Name: djmicrosip-polizas
Version: 1.0.0
Summary: Separa Ventas de Microsip
Home-page: UNKNOWN
Author: Servicios de Ingenieria Computacional
Author-email: soporte@siccomputacion.com
License: BSD License
Platform: UNKNOWN
Classifier: Environment :: Web Environment
Classifier: Framework :: Django
Classifier: Intended Audience :: Developers
Classifier: License :: OSI Approved :: BSD License
Classifier: Operating System :: OS Independent
Classifier: Programming Language :: Python
Classifier: Programming Language :: Python :: 2.6
Classifier: Programming Language :: Python :: 2.7
Classifier: Topic :: Internet :: WWW/HTTP
Classifier: Topic :: Internet :: WWW/HTTP :: Dynamic Content
